firestarter/__init__.py
firestarter/avr_tool.py
firestarter/config.py
firestarter/constants.py
firestarter/database.py
firestarter/eprom_info.py
firestarter/eprom_operations.py
firestarter/firmware.py
firestarter/hardware.py
firestarter/ic_layout.py
firestarter/logging_utils.py
firestarter/main.py
firestarter/serial_comm.py
firestarter/utils.py
firestarter/data/database_generated.json
firestarter/data/database_overrides.json
firestarter/data/pin-maps.json
firestarter-2.0.7.dist-info/licenses/LICENSE
firestarter-2.0.7.dist-info/METADATA
firestarter-2.0.7.dist-info/WHEEL
firestarter-2.0.7.dist-info/entry_points.txt
firestarter-2.0.7.dist-info/top_level.txt
firestarter-2.0.7.dist-info/RECORD
