Metadata-Version: 2.4
Name: firestarter
Version: 2.0.7
Summary: EPROM programmer software for the Relatively Universal ROM Programmer
Author-email: Henrik Olsson <henols@gmail.com>
Project-URL: Homepage, https://github.com/henols/firestarter_app
Keywords: firestarter,eprom,rom,eeprom,flash,programmer,arduino,electronics,retro computing,retro game console,commodore,atari,apple,c64,nes
Classifier: Environment :: Console
Classifier: Intended Audience :: Developers
Classifier: Intended Audience :: End Users/Desktop
Classifier: License :: OSI Approved :: MIT License
Classifier: Operating System :: OS Independent
Classifier: Programming Language :: Python :: 3
Classifier: Programming Language :: Python :: 3.9
Classifier: Programming Language :: Python :: 3.10
Classifier: Programming Language :: Python :: 3.11
Classifier: Programming Language :: Python :: 3.12
Classifier: Topic :: Scientific/Engineering
Classifier: Topic :: Software Development :: Embedded Systems
Classifier: Topic :: System :: Hardware :: Hardware Drivers
Requires-Python: >=3.9
License-File: LICENSE
Requires-Dist: pyserial>=3.5
Requires-Dist: requests>=2.20
Requires-Dist: tqdm>=4.60
Requires-Dist: argcomplete>=3.6.2
Requires-Dist: rich>=14.0
Dynamic: license-file
